odoo/addons/sale_order_archive/README.rst
odoo/addons/sale_order_archive/__init__.py
odoo/addons/sale_order_archive/__manifest__.py
odoo/addons/sale_order_archive/i18n/ca.po
odoo/addons/sale_order_archive/i18n/de.po
odoo/addons/sale_order_archive/i18n/es.po
odoo/addons/sale_order_archive/i18n/it.po
odoo/addons/sale_order_archive/i18n/nl.po
odoo/addons/sale_order_archive/i18n/pt.po
odoo/addons/sale_order_archive/i18n/pt_BR.po
odoo/addons/sale_order_archive/i18n/sale_order_archive.pot
odoo/addons/sale_order_archive/i18n/zh_CN.po
odoo/addons/sale_order_archive/models/__init__.py
odoo/addons/sale_order_archive/models/sale_order.py
odoo/addons/sale_order_archive/readme/CONTRIBUTORS.md
odoo/addons/sale_order_archive/readme/DESCRIPTION.md
odoo/addons/sale_order_archive/readme/INSTALL.md
odoo/addons/sale_order_archive/readme/USAGE.md
odoo/addons/sale_order_archive/static/description/icon.png
odoo/addons/sale_order_archive/static/description/index.html
odoo/addons/sale_order_archive/tests/__init__.py
odoo/addons/sale_order_archive/tests/test_sale_order_archive.py
odoo/addons/sale_order_archive/views/sale_order.xml
odoo_addon_sale_order_archive-18.0.1.0.0.4.dist-info/METADATA
odoo_addon_sale_order_archive-18.0.1.0.0.4.dist-info/WHEEL
odoo_addon_sale_order_archive-18.0.1.0.0.4.dist-info/top_level.txt
odoo_addon_sale_order_archive-18.0.1.0.0.4.dist-info/RECORD
